gtas_python_core/__init__.py
gtas_python_core/gtastest.py
gtas_python_core/wawa.py
library/__init__.py
library/gtastest.py
library/wawa.py
gtas_python_core-0.5.15.dist-info/METADATA
gtas_python_core-0.5.15.dist-info/WHEEL
gtas_python_core-0.5.15.dist-info/top_level.txt
gtas_python_core-0.5.15.dist-info/RECORD
