Metadata-Version: 2.1
Name: gtas-python-core
Version: 0.5.15
Summary: Gmarket Test Automation Solution
Home-page: http://github.ebaykorea.com/test-automation/gtas_python_core
Author: taeshik.kim
Author-email: taeshkim@gmarket.com
License: UNKNOWN
Keywords: gmarket
Platform: UNKNOWN
Classifier: Programming Language :: Python :: 3
Classifier: Programming Language :: Python :: 3.2
Classifier: Programming Language :: Python :: 3.3
Classifier: Programming Language :: Python :: 3.4
Classifier: Programming Language :: Python :: 3.5
Classifier: Programming Language :: Python :: 3.6
Classifier: Programming Language :: Python :: 3.7
Classifier: Programming Language :: Python :: 3.8
Classifier: Programming Language :: Python :: 3.9
Classifier: Programming Language :: Python :: 3.10
Classifier: Programming Language :: Python :: 3.11
Requires-Python: >=3
